<?xml version="1.0" encoding="utf-8"?>
<publishData>
  <publishProfile publishUrl="D:\GitSource\ZYWeb\Published" deleteExistingFiles="True" ftpAnonymousLogin="False" ftpPassiveMode="True" msdeploySite="" msdeploySiteID="" msdeployRemoteSitePhysicalPath="" msdeployAllowUntrustedCertificate="False" msdeploySkipExtraFilesOnServer="True" msdeployMarkAsApp="False" profileName="配置文件1" publishMethod="FileSystem" replaceMatchingFiles="False" userName="" savePWD="False" userPWD="" SelectedForPublish="True">
    <file relUrl="Silverlight.js" publishTime="07/19/2012 14:40:51" />
    <file relUrl="bin/ZYSoft.Comm.dll" publishTime="07/19/2012 15:05:04" />
    <file relUrl="bin/ZYSoft.Comm.pdb" publishTime="07/19/2012 15:05:04" />
    <file relUrl="indexSL.html" publishTime="07/19/2012 14:40:49" />
    <file relUrl="image/2.jpg" publishTime="07/19/2012 10:40:00" />
    <file relUrl="bin/ZYSoft.ORM.pdb" publishTime="07/19/2012 15:05:06" />
    <file relUrl="bin/Iesi.Collections.dll" publishTime="07/19/2012 10:40:00" />
    <file relUrl="bin/Web.dll" publishTime="07/19/2012 15:06:05" />
    <file relUrl="bin/ZYSoft.SQLDAL.dll" publishTime="07/19/2012 15:05:05" />
    <file relUrl="bin/ZYSoft.SQLDAL.pdb" publishTime="07/19/2012 15:05:05" />
    <file relUrl="image/Connect_logo_5.png" publishTime="07/19/2012 14:37:54" />
    <file relUrl="bin/ZYSoft.ORM.dll" publishTime="07/19/2012 15:05:06" />
    <file relUrl="Default.aspx" publishTime="07/19/2012 10:40:00" />
    <file relUrl="image/3.jpg" publishTime="07/19/2012 10:40:00" />
    <file relUrl="ClientBin/SilverlightUI.xap" publishTime="07/19/2012 15:04:54" />
    <file relUrl="bin/Web.pdb" publishTime="07/19/2012 15:06:05" />
    <file relUrl="bin/Iesi.Collections.xml" publishTime="07/19/2012 10:40:00" />
    <file relUrl="bin/ConfOrm.dll" publishTime="07/19/2012 10:40:00" />
    <file relUrl="image/1.jpg" publishTime="07/19/2012 10:40:00" />
    <file relUrl="bin/NHibernate.ByteCode.LinFu.dll" publishTime="07/19/2012 10:40:00" />
    <file relUrl="bin/ZYSoft.BLL.dll" publishTime="07/19/2012 15:05:07" />
    <file relUrl="Web.config" publishTime="07/19/2012 15:05:33" />
    <file relUrl="bin/NHibernate.ByteCode.LinFu.xml" publishTime="07/19/2012 10:40:00" />
    <file relUrl="index.htm" publishTime="07/19/2012 14:37:54" />
    <file relUrl="bin/ZYSoft.BLL.pdb" publishTime="07/19/2012 15:05:07" />
    <file relUrl="bin/NHibernate.xml" publishTime="07/19/2012 10:40:00" />
    <file relUrl="bin/NHibernate.dll" publishTime="07/19/2012 10:40:00" />
    <file relUrl="bin/LinFu.DynamicProxy.dll" publishTime="07/19/2012 10:40:00" />
  </publishProfile>
</publishData>